uuid_primary_key
django_uuid_primary_key
