Metadata-Version: 1.1
Name: django-uuid-primary-key
Version: 1.0.2
Summary: A simple Django model utility that provides to store primary key id as uuid.
Home-page: https://github.com/vaibhavmule/django-uuid-primary-key
Author: Vaibhav Mule
Author-email: vaibhavmule135@gmail.com
License: MIT License
Platform: UNKNOWN
Classifier: Environment :: Web Environment
Classifier: Framework :: Django
Classifier: Framework :: Django :: 2.0
Classifier: Intended Audience :: Developers
Classifier: License :: OSI Approved :: MIT License
Classifier: Operating System :: OS Independent
Classifier: Programming Language :: Python
Classifier: Programming Language :: Python :: 3.5
Classifier: Programming Language :: Python :: 3.6
